<?xml version="1.0" encoding="UTF-8"?>
<ServerManagerConfiguration>
  <ProxyGroup name="filters">
    <SourceProxy name="ttkBlockAggregator" class="ttkBlockAggregator" label="TTK BlockAggregator">
      <Documentation long_help="ttkBlockAggregator" short_help="ttkBlockAggregator">
        This filter appends every input vtkDataObject as a block to an output vtkMultiBlockDataSet.
      </Documentation>

      <InputProperty name="Input" port_index="0" clean_command="RemoveAllInputs" command="AddInputConnection" multiple_input="1">
        <ProxyGroupDomain name="groups">
          <Group name="sources" />
          <Group name="filters" />
        </ProxyGroupDomain>
        <Documentation>vtkDataObjects that will be added as blocks.</Documentation>
      </InputProperty>

      <IntVectorProperty name="FlattenInput" command="SetFlattenInput" number_of_elements="1" default_values="1">
        <BooleanDomain name="bool" />
        <Documentation>If enabled and if the input vtkDataObject is a 'vtkMultiBlockDataSet' then this filter will add its blocks to the output and not the vtkMultiBlockDataSet itself.</Documentation>
      </IntVectorProperty>
      <IntVectorProperty name="Decompose" command="SetDecompose" number_of_elements="1" default_values="0">
        <BooleanDomain name="bool" />
        <Documentation>TODO.</Documentation>
      </IntVectorProperty>
      <IntVectorProperty name="ForceReset" command="SetForceReset" number_of_elements="1" default_values="0">
        <BooleanDomain name="bool" />
        <Hints>
          <PropertyWidgetDecorator type="GenericDecorator" mode="visibility" property="Decompose" value="0" />
        </Hints>
        <Documentation>Force deletion of previously aggregated data.</Documentation>
      </IntVectorProperty>
      <StringVectorProperty name="InputArray" command="SetInputArrayToProcess" element_types="0 0 0 0 2" number_of_elements="5">
        <ArrayListDomain attribute_type="Scalars" name="array_list">
          <RequiredProperties>
            <Property function="Input" name="Input" />
          </RequiredProperties>
        </ArrayListDomain>
        <Hints>
          <PropertyWidgetDecorator type="GenericDecorator" mode="visibility" property="Decompose" value="1" />
        </Hints>
        <Documentation>TODO.</Documentation>
      </StringVectorProperty>

      ${DEBUG_WIDGETS}

      <Hints>
        <ShowInMenu category="TTK - Pipeline" />
      </Hints>
    </SourceProxy>
  </ProxyGroup>
</ServerManagerConfiguration>